{
    "GameObject": [
        {
            "EntityId": 0,
            "Transform": {
                "parent": -1,
                "position": {
                    "x": -3.66194224357605,
                    "y": 9.884419441223145,
                    "z": -3.1622323989868164
                },
                "rotate": {
                    "W": 0.9151856899261475,
                    "X": 0.36768195033073425,
                    "Y": 0.15316255390644073,
                    "Z": -0.061534080654382706
                },
                "scale": {
                    "x": 1.0,
                    "y": 1.0,
                    "z": 1.0
                }
            },
            "classType": "Camera",
            "name": "Camera",
            "tag": 0
        },
        {
            "EntityId": 1,
            "Transform": {
                "parent": -1,
                "position": {
                    "x": 0.0,
                    "y": 0.0,
                    "z": 0.0
                },
                "rotate": {
                    "W": 1.0,
                    "X": 0.0,
                    "Y": 0.0,
                    "Z": 0.0
                },
                "scale": {
                    "x": 1.0,
                    "y": 1.0,
                    "z": 1.0
                }
            },
            "classType": "Camera",
            "name": "Camera",
            "tag": 0
        },
        {
            "Collider": {
                "center": {
                    "x": 0.0,
                    "y": 0.0,
                    "z": 10.0
                },
                "colliderTag": 0,
                "colliderType": 2,
                "extents": {
                    "x": 0.5,
                    "y": 0.5,
                    "z": 0.5
                },
                "isStatic": false,
                "radius": 0.5
            },
            "EntityId": 2,
            "MeshRenderer": {
                "layer": 255,
                "meshFileName": "Model/Box.fbx",
                "meshHandle": 3,
                "shaderType": 2
            },
            "Transform": {
                "parent": -1,
                "position": {
                    "x": -2.8340914249420166,
                    "y": 3.1886250972747803,
                    "z": 10.0
                },
                "rotate": {
                    "W": 1.0,
                    "X": -0.0,
                    "Y": 0.0,
                    "Z": -0.0
                },
                "scale": {
                    "x": 1.0,
                    "y": 1.0,
                    "z": 1.0
                }
            },
            "classType": "Box3D",
            "name": "Box3D (0)",
            "tag": 0
        },
        {
            "Collider": {
                "center": {
                    "x": 0.0,
                    "y": 0.0,
                    "z": 10.0
                },
                "colliderTag": 0,
                "colliderType": 2,
                "extents": {
                    "x": 0.5,
                    "y": 0.5,
                    "z": 0.5
                },
                "isStatic": false,
                "radius": 0.5
            },
            "EntityId": 3,
            "MeshRenderer": {
                "layer": 255,
                "meshFileName": "Model/Box.fbx",
                "meshHandle": 3,
                "shaderType": 2
            },
            "Transform": {
                "parent": -1,
                "position": {
                    "x": 0.0,
                    "y": 0.0,
                    "z": 10.0
                },
                "rotate": {
                    "W": 1.0,
                    "X": -0.0,
                    "Y": 0.0,
                    "Z": -0.0
                },
                "scale": {
                    "x": 13.085921287536621,
                    "y": 1.0,
                    "z": 15.132831573486328
                }
            },
            "classType": "Box3D",
            "name": "Box3D (1)",
            "tag": 0
        }
    ]
}